{
  "version": "0.0.1",
  "description": "A Metamask Snap for managing and using Opact.",
  "proposedName": "Opact Wallet Snap",
  "repository": {
    "type": "git",
    "url": "https://github.com/MetaMask/template-snap-monorepo.git"
  },
  "source": {
    "shasum": "eQt97hq2KXiL7jyFKqIONk8XlQ4OPBBpjgUSHeyA7g4=",
    "location": {
      "npm": {
        "filePath": "dist/bundle.js",
        "iconPath": "images/icon.svg",
        "packageName": "snap",
        "registry": "https://registry.npmjs.org/"
      }
    }
  },
  "initialPermissions": {
    "endowment:rpc": {
      "dapps": true,
      "snaps": false
    },
    "endowment:ethereum-provider": {},
    "endowment:webassembly": {},
    "snap_notify": {},
    "snap_dialog": {},
    "snap_manageState": {},
    "snap_getEntropy": {}
  },
  "manifestVersion": "0.1"
}
